AUTHORS
ChangeLog
LICENSE
README.rst
announce.rst
setup.cfg
setup.py
test_ca_certs_locater.py
tox.ini
ca_certs_locater/__init__.py
httplib2.system_ca_certs_locater.egg-info/PKG-INFO
httplib2.system_ca_certs_locater.egg-info/SOURCES.txt
httplib2.system_ca_certs_locater.egg-info/dependency_links.txt
httplib2.system_ca_certs_locater.egg-info/not-zip-safe
httplib2.system_ca_certs_locater.egg-info/top_level.txt