Metadata-Version: 1.1
Name: httplib2.system-ca-certs-locater
Version: 0.1.1
Summary: Plug in to httplib2 to tell it to use the certificate authority file from the base OS instead of the one in the httplib2 package
Home-page: https://github.com/dreamhost/httplib2-ca_certs_locater
Author: New Dream Network, LLC (DreamHost)
Author-email: dev-community@dreamhost.com
License: UNKNOWN
Platform: UNKNOWN
Classifier: Intended Audience :: Information Technology
Classifier: Intended Audience :: System Administrators
Classifier: License :: OSI Approved :: Apache Software License
Classifier: Operating System :: POSIX :: Linux
Classifier: Programming Language :: Python
Classifier: Programming Language :: Python :: 2
Classifier: Programming Language :: Python :: 2.6
Classifier: Programming Language :: Python :: 2.7
Classifier: Topic :: System :: Monitoring
